ropper/__init__.py
ropper/__main__.py
ropper/arch.py
ropper/console.py
ropper/gadget.py
ropper/options.py
ropper/rop.py
ropper/search.py
ropper/semantic.py
ropper/service.py
ropper/z3helper.py
ropper/common/__init__.py
ropper/common/abstract.py
ropper/common/coloredstring.py
ropper/common/enum.py
ropper/common/error.py
ropper/common/utils.py
ropper/loaders/__init__.py
ropper/loaders/elf.py
ropper/loaders/loader.py
ropper/loaders/mach_o.py
ropper/loaders/pe.py
ropper/loaders/raw.py
ropper/printer/__init__.py
ropper/printer/elfprinter.py
ropper/printer/machprinter.py
ropper/printer/peprinter.py
ropper/printer/printer.py
ropper/printer/rawprinter.py
ropper/ropchain/__init__.py
ropper/ropchain/ropchain.py
ropper/ropchain/arch/__init__.py
ropper/ropchain/arch/ropchainx86.py
ropper/ropchain/arch/ropchainx86_64.py
ropper2-2.0.10.dist-info/AUTHORS
ropper2-2.0.10.dist-info/COPYING
ropper2-2.0.10.dist-info/METADATA
ropper2-2.0.10.dist-info/WHEEL
ropper2-2.0.10.dist-info/entry_points.txt
ropper2-2.0.10.dist-info/top_level.txt
ropper2-2.0.10.dist-info/RECORD
